flake8_no_unnecessary_fstrings.py
flake8_no_unnecessary_fstrings-1.0.1.dist-info/LICENSE
flake8_no_unnecessary_fstrings-1.0.1.dist-info/METADATA
flake8_no_unnecessary_fstrings-1.0.1.dist-info/WHEEL
flake8_no_unnecessary_fstrings-1.0.1.dist-info/entry_points.txt
flake8_no_unnecessary_fstrings-1.0.1.dist-info/top_level.txt
flake8_no_unnecessary_fstrings-1.0.1.dist-info/RECORD
