Metadata-Version: 2.1
Name: flake8-no-unnecessary-fstrings
Version: 1.0.1
Summary: A flake8 plugin to ban f-strings
Home-page: https://github.com/northisup/flake8-no-unnecessary-fstrings
Author: adam hitchcock
Author-email: adam+python@northisup.com
License: ISCL
Project-URL: Changelog, https://github.com/northisup/flake8-no-unnecessary-fstrings/blob/master/HISTORY.rst
Keywords: flake8
Platform: UNKNOWN
Classifier: Development Status :: 5 - Production/Stable
Classifier: Framework :: Flake8
Classifier: Intended Audience :: Developers
Classifier: License :: OSI Approved :: ISC License (ISCL)
Classifier: Natural Language :: English
Classifier: Programming Language :: Python :: 3 :: Only
Classifier: Programming Language :: Python :: 3
Classifier: Programming Language :: Python :: 3.6
Classifier: Programming Language :: Python :: 3.7
Classifier: Programming Language :: Python :: 3.8
Classifier: Programming Language :: Python :: 3.9
Requires-Python: >=3.6
Requires-Dist: flake8 (!=3.2.0,<4,>=3.0)
Requires-Dist: importlib-metadata ; python_version < "3.8"
